agent_sprint_testkit-0.3.1.dist-info/licenses/LICENSE
astk/__init__.py
astk/chaos.py
astk/cli.py
astk/evals_integration.py
astk/metrics.py
astk/persona.py
astk/runner.py
astk/schema.py
astk/benchmarks/__init__.py
astk/benchmarks/metrics.py
astk/benchmarks/runner.py
astk/benchmarks/visualization.py
scripts/__init__.py
scripts/simple_benchmark.py
scripts/simple_run.py
agent_sprint_testkit-0.3.1.dist-info/METADATA
agent_sprint_testkit-0.3.1.dist-info/WHEEL
agent_sprint_testkit-0.3.1.dist-info/entry_points.txt
agent_sprint_testkit-0.3.1.dist-info/top_level.txt
agent_sprint_testkit-0.3.1.dist-info/RECORD
